destigmatizer/__init__.py
destigmatizer/analyzers.py
destigmatizer/classifiers.py
destigmatizer/clients.py
destigmatizer/config_manager.py
destigmatizer/core.py
destigmatizer/rewriters.py
destigmatizer/utils.py
destigmatizer/tests/__init__.py
destigmatizer/tests/run_all_tests.py
destigmatizer/tests/test_drug_classifier.py
destigmatizer/tests/test_rewriter.py
destigmatizer/tests/test_stigma_classifier.py
destigmatizer/tests/test_text_analyzer.py
destigmatizer/tests/test_workflow.py
destigmatizer/tests/utils.py
destigmatizer-0.0.12.dist-info/licenses/LICENSE
destigmatizer-0.0.12.dist-info/METADATA
destigmatizer-0.0.12.dist-info/WHEEL
destigmatizer-0.0.12.dist-info/top_level.txt
destigmatizer-0.0.12.dist-info/RECORD
