Metadata-Version: 2.4
Name: destigmatizer
Version: 0.0.12
Summary: An llm-powered platform-agnostic language utility for destigmatizing drug language
Author-email: Layla Bouzoubaa <author@example.com>, Muqi Guo <author@example.com>, Joseph Trybala <author@example.com>
Maintainer-email: Layla Bouzoubaa <author@example.com>
License: BSD-3-Clause
Project-URL: Homepage, https://github.com/labouz/reframe
Project-URL: Issues, https://github.com/labouz/reframe/issues
Classifier: Programming Language :: Python :: 3
Classifier: Operating System :: OS Independent
Requires-Python: >=3.8
License-File: LICENSE
Requires-Dist: nltk
Requires-Dist: lexicalrichness
Dynamic: license-file
